{
  "pools": [
    {
      "rolls": 1,
      "bonus_rolls": 0,
      "entries": [
        {
          "type": "minecraft:item",
          "weight": 40,
          "name": "minecraft:calcite"
        },
            {
              "type": "minecraft:item",
              "weight": 20,
              "name": "moreweaponry:moon_stone_dust",
              "functions": [
                {
                  "function": "minecraft:set_count",
                  "count": 1,
                  "add": true
                }
              ]
            }
          ],
          "conditions": [
            {
              "condition": "minecraft:random_chance",
              "chance": 0.1
            }
          ]
        }
      ]
    }
  ]
}
